{
    "MEGCoordinateSystem": "ElektaNeuromag",
    "MEGCoordinateUnits": "m",
    "MEGCoordinateSystemDescription": "RAS orientation and the origin between the ears",
    "HeadCoilCoordinates": {
        "NAS": [
            5.587935447692871e-09,
            0.0909845381975174,
            3.725290298461914e-09
        ],
        "LPA": [
            -0.06879772990942001,
            -2.9802322387695312e-08,
            3.725290298461914e-09
        ],
        "RPA": [
            0.0637364462018013,
            -2.9802322387695312e-08,
            -3.725290298461914e-09
        ],
        "coil1": [
            -0.04794827848672867,
            0.08083203434944153,
            0.054095424711704254
        ],
        "coil2": [
            -0.004081089980900288,
            0.09797880053520203,
            0.05829858034849167
        ],
        "coil3": [
            0.04456983134150505,
            0.08396637439727783,
            0.049398623406887054
        ],
        "coil4": [
            -0.06677699089050293,
            -0.028778642416000366,
            -0.002343412023037672
        ],
        "coil5": [
            0.05962861329317093,
            -0.027988135814666748,
            -0.007045779377222061
        ]
    },
    "HeadCoilCoordinateSystem": "ElektaNeuromag",
    "HeadCoilCoordinateUnits": "m"
}
